eksrollup/__init__.py
eksrollup/__main__.py
eksrollup/cli.py
eksrollup/config.py
eksrollup/lib/__init__.py
eksrollup/lib/aws.py
eksrollup/lib/exceptions.py
eksrollup/lib/k8s.py
eksrollup/lib/logger.py
eks_rolling_update-1.1.8.dist-info/LICENSE
eks_rolling_update-1.1.8.dist-info/METADATA
eks_rolling_update-1.1.8.dist-info/WHEEL
eks_rolling_update-1.1.8.dist-info/entry_points.txt
eks_rolling_update-1.1.8.dist-info/top_level.txt
eks_rolling_update-1.1.8.dist-info/RECORD
