Metadata-Version: 2.1
Name: eks-rolling-update
Version: 1.1.8
Summary: EKS Rolling Update is a utility for updating the launch configuration or template of worker nodes in an EKS cluster.
Home-page: https://github.com/hellofresh/eks-rolling-update
Author: Craig Huber, Nicolas Bélanger, Sam Weston & contributors
Author-email: ch@hellofresh.com
Maintainer: Craig Huber & contributors
Maintainer-email: ch@hellofresh.com
License: Apache License, Version 2.0
Platform: UNKNOWN
Classifier: Development Status :: 5 - Production/Stable
Classifier: Environment :: Console
Classifier: Intended Audience :: Developers
Classifier: License :: OSI Approved :: Apache Software License
Classifier: Programming Language :: Python
Classifier: Programming Language :: Python :: 3.7
Classifier: Programming Language :: Python :: 3.8
Requires-Python: >=3.7
Requires-Dist: boto3 (>=1.9.246)
Requires-Dist: kubernetes (>=10.0.1)
Requires-Dist: python-dotenv (>=0.10.2)
